Metadata-Version: 2.1
Name: iftc
Version: 1.2.6
Summary: Spelling Correction for Vietnamese Informal Text
Home-page: https://gitlab.ftech.ai/nlp/research/ift-correction
Author: namph
Author-email: namph@ftech.ai
License: MIT
Classifier: Environment :: Console
Classifier: Intended Audience :: Developers
Classifier: Intended Audience :: Information Technology
Classifier: Intended Audience :: Education
Classifier: Intended Audience :: Science/Research
Classifier: License :: OSI Approved :: MIT License
Classifier: Natural Language :: Vietnamese
Classifier: Operating System :: OS Independent
Classifier: Programming Language :: Python :: 3
Requires-Python: >=3.4
Requires-Dist: nltk ==3.5
Requires-Dist: pandas
Requires-Dist: xlrd
Requires-Dist: dill
Requires-Dist: thefuzz
